CHANGES.txt
README.txt
TODO.txt
setup.py
collective/__init__.py
collective.salesforce.authplugin.egg-info/PKG-INFO
collective.salesforce.authplugin.egg-info/SOURCES.txt
collective.salesforce.authplugin.egg-info/dependency_links.txt
collective.salesforce.authplugin.egg-info/namespace_packages.txt
collective.salesforce.authplugin.egg-info/not-zip-safe
collective.salesforce.authplugin.egg-info/requires.txt
collective.salesforce.authplugin.egg-info/top_level.txt
collective/salesforce/__init__.py
collective/salesforce/authplugin/__init__.py
collective/salesforce/authplugin/config.py
collective/salesforce/authplugin/configure.zcml
collective/salesforce/authplugin/encrypt.py
collective/salesforce/authplugin/encrypt.txt
collective/salesforce/authplugin/interfaces.py
collective/salesforce/authplugin/Extensions/__init__.py
collective/salesforce/authplugin/Extensions/install.py
collective/salesforce/authplugin/docs/customizing_personalize.txt
collective/salesforce/authplugin/mixins/__init__.py
collective/salesforce/authplugin/mixins/authmixin.py
collective/salesforce/authplugin/mixins/propertymgmtmixin.py
collective/salesforce/authplugin/mixins/useraddermixin.py
collective/salesforce/authplugin/mixins/userenumerationmixin.py
collective/salesforce/authplugin/mixins/usermgmtmixin.py
collective/salesforce/authplugin/plugins/__init__.py
collective/salesforce/authplugin/plugins/base.py
collective/salesforce/authplugin/plugins/sfausermanager.py
collective/salesforce/authplugin/tests/__init__.py
collective/salesforce/authplugin/tests/base.py
collective/salesforce/authplugin/tests/configuration_functional.txt
collective/salesforce/authplugin/tests/test_authentication.py
collective/salesforce/authplugin/tests/test_caching.py
collective/salesforce/authplugin/tests/test_configuration.py
collective/salesforce/authplugin/tests/test_encrypt.py
collective/salesforce/authplugin/tests/test_functional.py
collective/salesforce/authplugin/tests/test_installation.py
collective/salesforce/authplugin/tests/test_interfaces.py
collective/salesforce/authplugin/tests/test_propertymanagement.py
collective/salesforce/authplugin/tests/test_reinstallation.py
collective/salesforce/authplugin/tests/test_uninstallation.py
collective/salesforce/authplugin/tests/test_useradder.py
collective/salesforce/authplugin/tests/test_userenumeration.py
collective/salesforce/authplugin/tests/test_usermanagement.py
