Metadata-Version: 1.0
Name: collective.salesforce.authplugin
Version: 1.5.2
Summary: Zope PAS plugin providing authentication against objects in Salesforce
Home-page: http://groups.google.com/group/plonesf
Author: Plone/Salesforce Integration Group
Author-email: plonesf@googlegroups.com
License: GPL
Keywords: Zope CMF Plone Salesforce.com CRM PAS authentication
Platform: UNKNOWN
Classifier: Framework :: Zope2
Classifier: Programming Language :: Python
Classifier: Development Status :: 5 - Production/Stable
